flashpass/__init__.py
flashpass/__main__.py
flashpass/cli.py
flashpass/crypto.py
flashpass/exceptions.py
flashpass/io.py
flashpass-1.0.1.dist-info/LICENSE
flashpass-1.0.1.dist-info/METADATA
flashpass-1.0.1.dist-info/WHEEL
flashpass-1.0.1.dist-info/entry_points.txt
flashpass-1.0.1.dist-info/RECORD
