Metadata-Version: 2.1
Name: flashpass
Version: 1.0.1
Summary: Encrypt & Decrypt FlashPass .fp files
Home-page: https://github.com/Septem151/flashpass
License: GPL-2.0-only
Keywords: security,passwords
Author: Carson Mullins
Author-email: carsonmullins@yahoo.com
Requires-Python: >=3.11,<4.0
Classifier: Development Status :: 4 - Beta
Classifier: Environment :: Console
Classifier: Intended Audience :: End Users/Desktop
Classifier: License :: OSI Approved :: GNU General Public License v2 (GPLv2)
Classifier: Programming Language :: Python :: 3
Classifier: Programming Language :: Python :: 3.11
Classifier: Programming Language :: Python :: 3 :: Only
Classifier: Topic :: Security
Classifier: Topic :: Utilities
Classifier: Typing :: Typed
Requires-Dist: cryptography (>=40.0.2,<41.0.0)
Requires-Dist: pyperclip (>=1.8.2,<2.0.0)
Project-URL: Repository, https://github.com/Septem151/flashpass
